easysam/cli.py
easysam/cloud.py
easysam/commondep.py
easysam/definitions.py
easysam/deploy.py
easysam/generate.py
easysam/init.py
easysam/inspect.py
easysam/load.py
easysam/prismarine.py
easysam/schemas.json
easysam/swagger.j2
easysam/template.j2
easysam/utils.py
easysam/validate_cloud.py
easysam/validate_schema.py
easysam-1.6.0.dist-info/METADATA
easysam-1.6.0.dist-info/WHEEL
easysam-1.6.0.dist-info/entry_points.txt
easysam-1.6.0.dist-info/licenses/LICENSE
easysam-1.6.0.dist-info/RECORD
