Metadata-Version: 2.4
Name: easysam
Version: 1.6.0
Summary: Opinionated Modular Cloud Deployment Tool (EasySAM)
Project-URL: Homepage, https://github.com/adsight-app/easysam
Project-URL: Changelog, https://github.com/adsight-app/easysam/blob/main/CHANGELOG.md
License-File: LICENSE
Requires-Python: >=3.12
Requires-Dist: aws-sam-cli>=1.138.0
Requires-Dist: boto3>=1.38.15
Requires-Dist: click>=8.2.0
Requires-Dist: jinja2-cli[yaml]>=0.8.2
Requires-Dist: jsonschema>=4.23.0
Requires-Dist: mergedeep>=1.3.4
Requires-Dist: prismarine>=1.4.1
Requires-Dist: python-benedict[yaml]>=0.34.1
Requires-Dist: rich>=13.9.4
